{"size": {"x_constraints": {"_start": 0, "_end": 25}, "y_constraints": {"_start": 0, "_end": 25}, "z_constraints": {"_start": 0, "_end": 10}}, "shapes": [{"visible": true, "_alpha": 0.19608, "_priority": 1, "_color": [123, 207, 226], "name": "a", "offset": 0, "x_offset": 0, "y_offset": 0, "layers": [{"x": [0.28024, 0.28024, 24.66803, 24.57087, 0.50695], "y": [24.25512, 24.25512, 24.43569, 0.46398, 0.46398], "_z": 0, "primary": true}, {"x": [0.28024, 0.28024, 24.66803, 24.57087, 0.50695], "y": [24.25512, 24.25512, 24.43569, 0.46398, 0.46398], "_z": 10, "primary": true}], "splits": [{"depth": 0, "angle": 0, "_line": {"a": {"x": null, "y": null, "z": null}, "b": {"x": null, "y": null, "z": null}}, "from_start": true, "a_offset_z": 0, "b_offset_z": 0}, {"depth": 0, "angle": 0, "_line": {"a": {"x": null, "y": null, "z": null}, "b": {"x": null, "y": null, "z": null}}, "from_start": true, "a_offset_z": 0, "b_offset_z": 0}], "sub_name": "", "parts_property": {}, "presence_intermediate_layers": true, "_filler": true}, {"visible": true, "_alpha": 0.9, "_priority": 1, "_color": [61, 189, 155], "name": "layer 1", "offset": 0, "x_offset": 0, "y_offset": 0, "layers": [{"x": [], "y": [], "_z": 0, "primary": true}], "splits": [{"depth": 0, "angle": 0, "_line": {"a": {"x": null, "y": null, "z": null}, "b": {"x": null, "y": null, "z": null}}, "from_start": true, "a_offset_z": 0, "b_offset_z": 0}, {"depth": 0, "angle": 0, "_line": {"a": {"x": null, "y": null, "z": null}, "b": {"x": null, "y": null, "z": null}}, "from_start": true, "a_offset_z": 0, "b_offset_z": 0}], "sub_name": "", "parts_property": {}, "presence_intermediate_layers": false, "_filler": true}], "roof_profile": {"points": [{"x": 14.62405, "y": 14.00698, "z": 5.0}], "interpolate_method": "cubic"}}